LICENSE
README.rst
setup.py
pytelibs/__init__.py
pytelibs/_globvals.py
pytelibs/_journal.py
pytelibs/_utils.py
pytelibs/version.py
pytelibs.egg-info/PKG-INFO
pytelibs.egg-info/SOURCES.txt
pytelibs.egg-info/dependency_links.txt
pytelibs.egg-info/requires.txt
pytelibs.egg-info/top_level.txt