Metadata-Version: 2.1
Name: pytelibs
Version: 1.2.220
Summary: Client library for Pytel
Home-page: https://github.com/kastaid/pytelibs
Author: Unknown
Author-email: unknownkz@outlook.co.id
License: AGPL
Keywords: pypi,pytelibs,python,pyrogram,telebot
Platform: UNKNOWN
Classifier: Development Status :: 5 - Production/Stable
Classifier: Intended Audience :: Developers
Classifier: Programming Language :: Python :: 3.8
Classifier: Programming Language :: Python :: 3.9
Classifier: Programming Language :: Python :: 3.10
Classifier: Operating System :: Unix
Requires-Python: >3.8
License-File: LICENSE
